researchacademic/__init__.py
researchacademic/fetcher.py
researchacademic/test_fetcher.py
researchacademic-0.9.2.dist-info/LICENSE
researchacademic-0.9.2.dist-info/METADATA
researchacademic-0.9.2.dist-info/WHEEL
researchacademic-0.9.2.dist-info/top_level.txt
researchacademic-0.9.2.dist-info/zip-safe
researchacademic-0.9.2.dist-info/RECORD
