Metadata-Version: 2.1
Name: researchacademic
Version: 0.9.2
Summary: A python library that aims to retrieve data from MicrosoftResearch Academic and parse data to human readable
Home-page: https://github.com/wyh/pymsresearch
Author: Samuel Wu
Author-email: samuel.yh.wu@gmail.com
License: MIT
Platform: UNKNOWN
Classifier: Development Status :: 4 - Beta
Classifier: Intended Audience :: Developers
Classifier: Intended Audience :: Science/Research
Classifier: Programming Language :: Python :: 3
Classifier: Topic :: Software Development :: Libraries :: Python Modules
Requires-Dist: requests
